excel_processor/__init__.py
stms_excel_processor-0.1.1.dist-info/METADATA
stms_excel_processor-0.1.1.dist-info/WHEEL
stms_excel_processor-0.1.1.dist-info/licenses/LICENSE
stms_excel_processor-0.1.1.dist-info/RECORD
