Metadata-Version: 2.4
Name: stms-excel-processor
Version: 0.1.1
Summary: Simple excel-processor.
Author-email: Tester <tester@example.com>
License: MIT
License-File: LICENSE
Keywords: excel,wrapper,xlsx
Classifier: Development Status :: 4 - Beta
Classifier: Intended Audience :: Developers
Classifier: License :: OSI Approved :: MIT License
Classifier: Programming Language :: Python :: 3
Classifier: Programming Language :: Python :: 3.10
Classifier: Programming Language :: Python :: 3.11
Classifier: Programming Language :: Python :: 3.12
Classifier: Topic :: Office/Business :: Financial :: Spreadsheet
Classifier: Topic :: Software Development :: Libraries :: Python Modules
Requires-Python: >=3.10
Requires-Dist: spire-xls-free==14.12.4
